Metadata-Version: 2.4
Name: ordeq_boto3
Version: 1.0.0
Author: Niels Neerhoff, Simon Brugman
Maintainer: Niels Neerhoff, Simon Brugman
License-Expression: MIT
Requires-Python: >=3.10
Requires-Dist: ordeq>=0.5.0
Requires-Dist: boto3
